gli/__init__.py
gli/cli.py
gli/utils.py
gli/commands/__init__.py
gli/commands/base.py
gli/commands/delete_environment.py
gli/commands/delete_variable.py
gli/commands/get_environment.py
gli/commands/get_project.py
gli/commands/get_variable.py
gli/commands/set_variable.py
gli/commands/toggle_registry.py
gli-0.0.4.dist-info/DESCRIPTION.rst
gli-0.0.4.dist-info/METADATA
gli-0.0.4.dist-info/RECORD
gli-0.0.4.dist-info/WHEEL
gli-0.0.4.dist-info/entry_points.txt
gli-0.0.4.dist-info/metadata.json
gli-0.0.4.dist-info/top_level.txt
